<?xml version="1.0" encoding="utf-8" ?>
<dwsync>
<file name="banip.tpl" server="G:/xampp/htdocs/dienhoa/" local="129900016660000000" remote="129900016660000000" />
<file name="bots.tpl" server="G:/xampp/htdocs/dienhoa/" local="129900016660000000" remote="129900016660000000" />
<file name="cronjobs_add.tpl" server="G:/xampp/htdocs/dienhoa/" local="129900016660000000" remote="129900016660000000" />
<file name="cronjobs_list.tpl" server="G:/xampp/htdocs/dienhoa/" local="129900016660000000" remote="129900016660000000" />
<file name="ftp.tpl" server="G:/xampp/htdocs/dienhoa/" local="129900016660000000" remote="129900016660000000" />
<file name="index.html" server="G:/xampp/htdocs/dienhoa/" local="129900016660000000" remote="129900016660000000" />
<file name="main.tpl" server="G:/xampp/htdocs/dienhoa/" local="129900016660000000" remote="129900016660000000" />
<file name="metatags.tpl" server="G:/xampp/htdocs/dienhoa/" local="129900016660000000" remote="129900016660000000" />
<file name="pagetitle.tpl" server="G:/xampp/htdocs/dienhoa/" local="129900016660000000" remote="129900016660000000" />
<file name="robots.tpl" server="G:/xampp/htdocs/dienhoa/" local="129900016660000000" remote="129900016660000000" />
<file name="smtp.tpl" server="G:/xampp/htdocs/dienhoa/" local="129900016660000000" remote="129900016660000000" />
<file name="statistics.tpl" server="G:/xampp/htdocs/dienhoa/" local="129900016640000000" remote="129900016640000000" />
<file name="system.tpl" server="G:/xampp/htdocs/dienhoa/" local="129900016640000000" remote="129900016640000000" />
<file name="uploadconfig.tpl" server="G:/xampp/htdocs/dienhoa/" local="129900016640000000" remote="129900016640000000" />
</dwsync>